gorse/__init__.py
PyGorse-0.4.9.dist-info/LICENSE
PyGorse-0.4.9.dist-info/METADATA
PyGorse-0.4.9.dist-info/WHEEL
PyGorse-0.4.9.dist-info/top_level.txt
PyGorse-0.4.9.dist-info/RECORD
