Metadata-Version: 2.2
Name: PyGorse
Version: 0.4.9
Summary: Python SDK for gorse recommender system
License-File: LICENSE
Requires-Dist: requests>=2.14.0
Requires-Dist: aiohttp>=3.8.3
Dynamic: description
Dynamic: description-content-type
Dynamic: requires-dist
Dynamic: summary
